<dcrgraph title="Running example" dataTypesStatus="hide" filterLevel="-1" insightFilter="false" zoomLevel="0" formGroupStyle="Normal" formLayoutStyle="Horizontal" formShowPendingCount="true" graphBG="#f1f6fe" graphType="0" exercise="false">
    <meta>
        <graph id="1624264" hash="AB88917251699313FD5CDE62E26FBD66" guid="6CA187F4-CBC5-4F1C-862B-F91362D88D8C" OwnerName="Jeppe Blomgren" OwnerId="136207" categoryId="7301" categoryTitle="Default" Keywords=""/>
        <revision id="3195212" type="minor" date="2023-05-11T17:45:36.653"/>
        <organization id="1" name="Community"/>
    </meta>
    <specification>
        <resources>
            <events>
                <event id="Request" computation="Request-computation">
                    <precondition message=""/>
                    <custom>
                        <visualization>
                            <location xLoc="300" yLoc="175"/>
                            <colors bg="#f9f7ed" textStroke="#000000" stroke="#cccccc"/>
                        </visualization>
                        <roles>
                            <role>Buyer</role>
                        </roles>
                        <readRoles>
                            <readRole>Seller</readRole>
                        </readRoles>
                        <groups>
                            <group/>
                        </groups>
                        <phases>
                            <phase/>
                        </phases>
                        <eventType/>
                        <eventScope>private</eventScope>
                        <eventTypeData/>
                        <eventDescription/>
                        <purpose/>
                        <guide/>
                        <insight use="false"/>
                        <level>1</level>
                        <sequence>1</sequence>
                        <costs>0</costs>
                        <eventData/>
                        <interfaces/>
                    </custom>
                </event>
                <event id="Quote" computation="Quote-computation">
                    <precondition message=""/>
                    <custom>
                        <visualization>
                            <location xLoc="600" yLoc="175"/>
                            <colors bg="#f9f7ed" textStroke="#000000" stroke="#cccccc"/>
                        </visualization>
                        <roles>
                            <role>Seller</role>
                        </roles>
                        <readRoles>
                            <readRole>Buyer</readRole>
                        </readRoles>
                        <groups>
                            <group/>
                        </groups>
                        <phases>
                            <phase/>
                        </phases>
                        <eventType/>
                        <eventScope>private</eventScope>
                        <eventTypeData/>
                        <eventDescription/>
                        <purpose/>
                        <guide/>
                        <insight use="false"/>
                        <level>1</level>
                        <sequence>2</sequence>
                        <costs>0</costs>
                        <eventData/>
                        <interfaces/>
                    </custom>
                </event>
                <event id="Order" computation="Order-computation">
                    <precondition message=""/>
                    <custom>
                        <visualization>
                            <location xLoc="300" yLoc="375"/>
                            <colors bg="#f9f7ed" textStroke="#000000" stroke="#cccccc"/>
                        </visualization>
                        <roles>
                            <role>Buyer</role>
                        </roles>
                        <readRoles>
                            <readRole>Seller</readRole>
                        </readRoles>
                        <groups>
                            <group/>
                        </groups>
                        <phases>
                            <phase/>
                        </phases>
                        <eventType/>
                        <eventScope>private</eventScope>
                        <eventTypeData/>
                        <eventDescription/>
                        <purpose/>
                        <guide/>
                        <insight use="false"/>
                        <level>1</level>
                        <sequence>3</sequence>
                        <costs>0</costs>
                        <eventData/>
                        <interfaces/>
                    </custom>
                </event>
                <event id="Ship" computation="Ship-computation">
                    <precondition message=""/>
                    <custom>
                        <visualization>
                            <location xLoc="600" yLoc="375"/>
                            <colors bg="#f9f7ed" textStroke="#000000" stroke="#cccccc"/>
                        </visualization>
                        <roles>
                            <role>Seller</role>
                        </roles>
                        <readRoles>
                            <readRole>Buyer</readRole>
                        </readRoles>
                        <groups>
                            <group/>
                        </groups>
                        <phases>
                            <phase/>
                        </phases>
                        <eventType/>
                        <eventScope>private</eventScope>
                        <eventTypeData/>
                        <eventDescription/>
                        <purpose/>
                        <guide/>
                        <insight use="false"/>
                        <level>1</level>
                        <sequence>4</sequence>
                        <costs>0</costs>
                        <eventData/>
                        <interfaces/>
                    </custom>
                </event>
                <event id="Item">
                    <precondition message=""/>
                    <custom>
                        <visualization>
                            <location xLoc="150" yLoc="175"/>
                            <colors bg="#f9f7ed" textStroke="#000000" stroke="#cccccc"/>
                        </visualization>
                        <roles>
                            <role>Buyer</role>
                        </roles>
                        <readRoles>
                            <readRole/>
                        </readRoles>
                        <groups>
                            <group/>
                        </groups>
                        <phases>
                            <phase/>
                        </phases>
                        <eventType/>
                        <eventScope>private</eventScope>
                        <eventTypeData/>
                        <eventDescription/>
                        <purpose/>
                        <guide/>
                        <insight use="false"/>
                        <level>1</level>
                        <sequence>5</sequence>
                        <costs>0</costs>
                        <eventData>
                            <dataType sequence="5" width="small" min="NaN" max="NaN" placeholder="" hinttext="">text</dataType>
                            <validationRules/>
                        </eventData>
                        <interfaces/>
                    </custom>
                </event>
                <event id="Budget">
                    <precondition message=""/>
                    <custom>
                        <visualization>
                            <location xLoc="150" yLoc="375"/>
                            <colors bg="#f9f7ed" textStroke="#000000" stroke="#cccccc"/>
                        </visualization>
                        <roles>
                            <role>Buyer</role>
                        </roles>
                        <readRoles>
                            <readRole/>
                        </readRoles>
                        <groups>
                            <group/>
                        </groups>
                        <phases>
                            <phase/>
                        </phases>
                        <eventType/>
                        <eventScope>private</eventScope>
                        <eventTypeData/>
                        <eventDescription/>
                        <purpose/>
                        <guide/>
                        <insight use="false"/>
                        <level>1</level>
                        <sequence>6</sequence>
                        <costs>0</costs>
                        <eventData>
                            <dataType sequence="6" width="small" min="NaN" max="NaN" placeholder="" hinttext="">int</dataType>
                            <validationRules/>
                        </eventData>
                        <interfaces/>
                    </custom>
                </event>
            </events>
            <subProcesses/>
            <distribution/>
            <labels>
                <label id="Request"/>
                <label id="Quote"/>
                <label id="Order"/>
                <label id="Ship"/>
                <label id="Item"/>
                <label id="Budget"/>
            </labels>
            <labelMappings>
                <labelMapping eventId="Request" labelId="Request"/>
                <labelMapping eventId="Quote" labelId="Quote"/>
                <labelMapping eventId="Order" labelId="Order"/>
                <labelMapping eventId="Ship" labelId="Ship"/>
                <labelMapping eventId="Item" labelId="Item"/>
                <labelMapping eventId="Budget" labelId="Budget"/>
            </labelMappings>
            <expressions>
                <expression id="Quote-path-Request--response" value="Quote = -1"/>
                <expression id="Order-path-Ship--response" value="Order &gt; 0"/>
                <expression id="Order-path-Ship--include" value="Order &gt; 0"/>
                <expression id="Quote-path-Order--include" value="Quote != -1"/>
                <expression id="Request-computation" value="Item"/>
                <expression id="Quote-computation" value="null"/>
                <expression id="Order-computation" value="Budget"/>
                <expression id="Ship-computation" value="null"/>
            </expressions>
            <variables/>
            <variableAccesses>
                <writeAccesses/>
            </variableAccesses>
            <custom>
                <keywords/>
                <roles>
                    <role description="" specification="">Buyer</role>
                    <role description="" specification="">Seller</role>
                </roles>
                <groups/>
                <phases/>
                <eventTypes/>
                <eventParameters/>
                <graphDetails>DCR Process</graphDetails>
                <graphDocumentation/>
                <graphLanguage>en-US</graphLanguage>
                <graphDomain>process</graphDomain>
                <graphFilters>
                    <filteredGroups/>
                    <filteredRoles/>
                    <filteredPhases/>
                </graphFilters>
                <hightlighterMarkup id="HLM"/>
                <highlighterMarkup>
                    <highlightLayers>
                        <highlightLayer default="true" name="description">DCR Process</highlightLayer>
                    </highlightLayers>
                    <highlights/>
                </highlighterMarkup>
            </custom>
        </resources>
        <constraints>
            <conditions>
                <condition sourceId="Ship" targetId="Order" filterLevel="1" description="" time="" groups=""/>
                <condition sourceId="Ship" targetId="Request" filterLevel="1" description="" time="" groups=""/>
                <condition sourceId="Item" targetId="Request" filterLevel="1" description="" time="" groups=""/>
                <condition sourceId="Budget" targetId="Order" filterLevel="1" description="" time="" groups=""/>
            </conditions>
            <responses>
                <response sourceId="Quote" targetId="Request" filterLevel="1" description="" time="" groups="" expressionId="Quote-path-Request--response"/>
                <response sourceId="Order" targetId="Ship" filterLevel="1" description="" time="" groups="" expressionId="Order-path-Ship--response"/>
                <response sourceId="Request" targetId="Quote" filterLevel="1" description="" time="" groups=""/>
            </responses>
            <coresponses/>
            <excludes>
                <exclude sourceId="Quote" targetId="Quote" filterLevel="1" description="" time="" groups=""/>
                <exclude sourceId="Ship" targetId="Ship" filterLevel="1" description="" time="" groups=""/>
            </excludes>
            <includes>
                <include sourceId="Order" targetId="Ship" filterLevel="1" description="" time="" groups="" expressionId="Order-path-Ship--include"/>
                <include sourceId="Quote" targetId="Order" filterLevel="1" description="" time="" groups="" expressionId="Quote-path-Order--include"/>
                <include sourceId="Request" targetId="Quote" filterLevel="1" description="" time="" groups=""/>
            </includes>
            <milestones>
                <milestone sourceId="Request" targetId="Order" filterLevel="1" description="" time="" groups=""/>
                <milestone sourceId="Quote" targetId="Order" filterLevel="1" description="" time="" groups=""/>
            </milestones>
            <updates/>
            <spawns/>
            <templateSpawns/>
        </constraints>
    </specification>
    <runtime>
        <custom>
            <globalMarking/>
        </custom>
        <marking>
            <globalStore/>
            <executed/>
            <included>
                <event id="Request"/>
                <event id="Item"/>
                <event id="Budget"/>
            </included>
            <pendingResponses>
                <event id="Request"/>
            </pendingResponses>
        </marking>
    </runtime>
</dcrgraph>
